tslearner/__init__.py
tslearner/core.c
tslearner/core.cpython-38-x86_64-linux-gnu.so
tslearner-0.1.3.dist-info/LICENSE
tslearner-0.1.3.dist-info/METADATA
tslearner-0.1.3.dist-info/WHEEL
tslearner-0.1.3.dist-info/top_level.txt
tslearner-0.1.3.dist-info/RECORD
