Metadata-Version: 2.1
Name: tslearner
Version: 0.1.3
Summary: Python package for time-series learning
Author: newton1666
Author-email: newton1666mira@gmail.com
Requires-Python: >=3.8,<3.9
License-File: LICENSE
